[
  {
    "source_name": "Anime Corner",
    "status": "ok",
    "fetched_count": 12,
    "persisted_count": 12,
    "error_count": 0,
    "consecutive_failures": 0,
    "last_run_at": "2026-05-08T00:14:30.755209Z",
    "last_success_at": "2026-05-08T00:14:30.755209Z",
    "last_error": null,
    "stale": false
  },
  {
    "source_name": "Anime Feminist",
    "status": "ok",
    "fetched_count": 12,
    "persisted_count": 12,
    "error_count": 0,
    "consecutive_failures": 0,
    "last_run_at": "2026-05-08T00:14:30.770455Z",
    "last_success_at": "2026-05-08T00:14:30.770455Z",
    "last_error": null,
    "stale": false
  },
  {
    "source_name": "Anime Hunch",
    "status": "ok",
    "fetched_count": 12,
    "persisted_count": 12,
    "error_count": 0,
    "consecutive_failures": 0,
    "last_run_at": "2026-05-08T00:14:30.788952Z",
    "last_success_at": "2026-05-08T00:14:30.788952Z",
    "last_error": null,
    "stale": false
  },
  {
    "source_name": "Anime Trending",
    "status": "ok",
    "fetched_count": 10,
    "persisted_count": 10,
    "error_count": 0,
    "consecutive_failures": 0,
    "last_run_at": "2026-05-08T00:14:30.795970Z",
    "last_success_at": "2026-05-08T00:14:30.795970Z",
    "last_error": null,
    "stale": false
  },
  {
    "source_name": "Automaton West",
    "status": "ok",
    "fetched_count": 6,
    "persisted_count": 6,
    "error_count": 0,
    "consecutive_failures": 0,
    "last_run_at": "2026-05-08T00:14:30.725087Z",
    "last_success_at": "2026-05-08T00:14:30.725087Z",
    "last_error": null,
    "stale": false
  },
  {
    "source_name": "Bandwagon Asia",
    "status": "ok",
    "fetched_count": 1,
    "persisted_count": 1,
    "error_count": 0,
    "consecutive_failures": 0,
    "last_run_at": "2026-05-08T00:14:30.687883Z",
    "last_success_at": "2026-05-08T00:14:30.687883Z",
    "last_error": null,
    "stale": false
  },
  {
    "source_name": "Crunchyroll News",
    "status": "ok",
    "fetched_count": 8,
    "persisted_count": 8,
    "error_count": 0,
    "consecutive_failures": 0,
    "last_run_at": "2026-05-08T00:14:30.764949Z",
    "last_success_at": "2026-05-08T00:14:30.764949Z",
    "last_error": null,
    "stale": false
  },
  {
    "source_name": "DualShockers",
    "status": "ok",
    "fetched_count": 3,
    "persisted_count": 3,
    "error_count": 0,
    "consecutive_failures": 0,
    "last_run_at": "2026-05-08T00:14:30.766978Z",
    "last_success_at": "2026-05-08T00:14:30.766978Z",
    "last_error": null,
    "stale": false
  },
  {
    "source_name": "Esports Insider",
    "status": "error",
    "fetched_count": 0,
    "persisted_count": 0,
    "error_count": 1,
    "consecutive_failures": 1,
    "last_run_at": "2026-05-08T00:14:30.803932Z",
    "last_success_at": null,
    "last_error": "Client error '403 Forbidden' for url 'https://esportsinsider.com/feed' For more information check: https://developer.mozilla.org/en-US/docs/Web/HTTP/Status/403",
    "stale": false
  },
  {
    "source_name": "Esports.gg",
    "status": "ok",
    "fetched_count": 5,
    "persisted_count": 5,
    "error_count": 0,
    "consecutive_failures": 0,
    "last_run_at": "2026-05-08T00:14:30.786531Z",
    "last_success_at": "2026-05-08T00:14:30.786531Z",
    "last_error": null,
    "stale": false
  },
  {
    "source_name": "Eventbrite SG Anime",
    "status": "ok",
    "fetched_count": 8,
    "persisted_count": 3,
    "error_count": 0,
    "consecutive_failures": 0,
    "last_run_at": "2026-05-08T00:14:30.804452Z",
    "last_success_at": "2026-05-08T00:14:30.804452Z",
    "last_error": null,
    "stale": false
  },
  {
    "source_name": "Eventbrite SG Gaming",
    "status": "ok",
    "fetched_count": 10,
    "persisted_count": 9,
    "error_count": 0,
    "consecutive_failures": 0,
    "last_run_at": "2026-05-08T00:14:30.808696Z",
    "last_success_at": "2026-05-08T00:14:30.808696Z",
    "last_error": null,
    "stale": false
  },
  {
    "source_name": "Final Fantasy XIV News",
    "status": "ok",
    "fetched_count": 12,
    "persisted_count": 12,
    "error_count": 0,
    "consecutive_failures": 0,
    "last_run_at": "2026-05-08T00:14:30.775702Z",
    "last_success_at": "2026-05-08T00:14:30.775702Z",
    "last_error": null,
    "stale": false
  },
  {
    "source_name": "Final Weapon",
    "status": "error",
    "fetched_count": 0,
    "persisted_count": 0,
    "error_count": 1,
    "consecutive_failures": 1,
    "last_run_at": "2026-05-08T00:14:30.730926Z",
    "last_success_at": null,
    "last_error": "Client error '403 Forbidden' for url 'https://finalweapon.net/feed/' For more information check: https://developer.mozilla.org/en-US/docs/Web/HTTP/Status/403",
    "stale": false
  },
  {
    "source_name": "Geek Culture",
    "status": "ok",
    "fetched_count": 1,
    "persisted_count": 1,
    "error_count": 0,
    "consecutive_failures": 0,
    "last_run_at": "2026-05-08T00:14:30.786095Z",
    "last_success_at": "2026-05-08T00:14:30.786095Z",
    "last_error": null,
    "stale": false
  },
  {
    "source_name": "Google News Anime And Manga",
    "status": "ok",
    "fetched_count": 10,
    "persisted_count": 6,
    "error_count": 0,
    "consecutive_failures": 0,
    "last_run_at": "2026-05-08T00:14:30.825269Z",
    "last_success_at": "2026-05-08T00:14:30.825269Z",
    "last_error": null,
    "stale": false
  },
  {
    "source_name": "Google News Anime Conventions",
    "status": "ok",
    "fetched_count": 9,
    "persisted_count": 8,
    "error_count": 0,
    "consecutive_failures": 0,
    "last_run_at": "2026-05-08T00:14:30.839543Z",
    "last_success_at": "2026-05-08T00:14:30.839543Z",
    "last_error": null,
    "stale": false
  },
  {
    "source_name": "Google News Artist Alley",
    "status": "ok",
    "fetched_count": 9,
    "persisted_count": 5,
    "error_count": 0,
    "consecutive_failures": 0,
    "last_run_at": "2026-05-08T00:14:30.837956Z",
    "last_success_at": "2026-05-08T00:14:30.837956Z",
    "last_error": null,
    "stale": false
  },
  {
    "source_name": "Google News HoyoFest",
    "status": "ok",
    "fetched_count": 11,
    "persisted_count": 11,
    "error_count": 0,
    "consecutive_failures": 0,
    "last_run_at": "2026-05-08T00:14:30.834239Z",
    "last_success_at": "2026-05-08T00:14:30.834239Z",
    "last_error": null,
    "stale": false
  },
  {
    "source_name": "Google News JRPG",
    "status": "ok",
    "fetched_count": 12,
    "persisted_count": 11,
    "error_count": 0,
    "consecutive_failures": 0,
    "last_run_at": "2026-05-08T00:14:30.818113Z",
    "last_success_at": "2026-05-08T00:14:30.818113Z",
    "last_error": null,
    "stale": false
  },
  {
    "source_name": "Google News JRPG Demo",
    "status": "ok",
    "fetched_count": 10,
    "persisted_count": 10,
    "error_count": 0,
    "consecutive_failures": 0,
    "last_run_at": "2026-05-08T00:14:30.822177Z",
    "last_success_at": "2026-05-08T00:14:30.822177Z",
    "last_error": null,
    "stale": false
  },
  {
    "source_name": "Google News Merch And Deals",
    "status": "ok",
    "fetched_count": 12,
    "persisted_count": 12,
    "error_count": 0,
    "consecutive_failures": 0,
    "last_run_at": "2026-05-08T00:14:30.830012Z",
    "last_success_at": "2026-05-08T00:14:30.830012Z",
    "last_error": null,
    "stale": false
  },
  {
    "source_name": "Google News SEA Anime Distributors",
    "status": "ok",
    "fetched_count": 1,
    "persisted_count": 1,
    "error_count": 0,
    "consecutive_failures": 0,
    "last_run_at": "2026-05-08T00:14:30.887543Z",
    "last_success_at": "2026-05-08T00:14:30.887543Z",
    "last_error": null,
    "stale": false
  },
  {
    "source_name": "Google News SEA Anime Exhibitions",
    "status": "ok",
    "fetched_count": 3,
    "persisted_count": 2,
    "error_count": 0,
    "consecutive_failures": 0,
    "last_run_at": "2026-05-08T00:14:30.876269Z",
    "last_success_at": "2026-05-08T00:14:30.876269Z",
    "last_error": null,
    "stale": false
  },
  {
    "source_name": "Google News SEA Anime Screenings",
    "status": "ok",
    "fetched_count": 7,
    "persisted_count": 7,
    "error_count": 0,
    "consecutive_failures": 0,
    "last_run_at": "2026-05-08T00:14:30.871612Z",
    "last_success_at": "2026-05-08T00:14:30.871612Z",
    "last_error": null,
    "stale": false
  },
  {
    "source_name": "Google News SEA Anime Stage Plays",
    "status": "ok",
    "fetched_count": 0,
    "persisted_count": 0,
    "error_count": 0,
    "consecutive_failures": 0,
    "last_run_at": "2026-05-08T00:14:30.887537Z",
    "last_success_at": "2026-05-08T00:14:30.887537Z",
    "last_error": null,
    "stale": false
  },
  {
    "source_name": "Google News SEA Arcade Prize Games",
    "status": "ok",
    "fetched_count": 0,
    "persisted_count": 0,
    "error_count": 0,
    "consecutive_failures": 0,
    "last_run_at": "2026-05-08T00:14:30.887539Z",
    "last_success_at": "2026-05-08T00:14:30.887539Z",
    "last_error": null,
    "stale": false
  },
  {
    "source_name": "Google News SEA Bushiroad TCG Festivals",
    "status": "ok",
    "fetched_count": 0,
    "persisted_count": 0,
    "error_count": 0,
    "consecutive_failures": 0,
    "last_run_at": "2026-05-08T00:14:30.887541Z",
    "last_success_at": "2026-05-08T00:14:30.887541Z",
    "last_error": null,
    "stale": false
  },
  {
    "source_name": "Google News SEA Capsule Toys",
    "status": "ok",
    "fetched_count": 7,
    "persisted_count": 7,
    "error_count": 0,
    "consecutive_failures": 0,
    "last_run_at": "2026-05-08T00:14:30.881766Z",
    "last_success_at": "2026-05-08T00:14:30.881766Z",
    "last_error": null,
    "stale": false
  },
  {
    "source_name": "Google News SEA Esports",
    "status": "ok",
    "fetched_count": 12,
    "persisted_count": 9,
    "error_count": 0,
    "consecutive_failures": 0,
    "last_run_at": "2026-05-08T00:14:30.827182Z",
    "last_success_at": "2026-05-08T00:14:30.827182Z",
    "last_error": null,
    "stale": false
  },
  {
    "source_name": "Google News SEA FFXIV",
    "status": "ok",
    "fetched_count": 9,
    "persisted_count": 9,
    "error_count": 0,
    "consecutive_failures": 0,
    "last_run_at": "2026-05-08T00:14:30.866677Z",
    "last_success_at": "2026-05-08T00:14:30.866677Z",
    "last_error": null,
    "stale": false
  },
  {
    "source_name": "Google News SEA Fighting Games",
    "status": "ok",
    "fetched_count": 6,
    "persisted_count": 6,
    "error_count": 0,
    "consecutive_failures": 0,
    "last_run_at": "2026-05-08T00:14:30.856108Z",
    "last_success_at": "2026-05-08T00:14:30.856108Z",
    "last_error": null,
    "stale": false
  },
  {
    "source_name": "Google News SEA Gacha",
    "status": "ok",
    "fetched_count": 10,
    "persisted_count": 10,
    "error_count": 0,
    "consecutive_failures": 0,
    "last_run_at": "2026-05-08T00:14:30.842168Z",
    "last_success_at": "2026-05-08T00:14:30.842168Z",
    "last_error": null,
    "stale": false
  },
  {
    "source_name": "Google News SEA Gunpla",
    "status": "ok",
    "fetched_count": 12,
    "persisted_count": 4,
    "error_count": 0,
    "consecutive_failures": 0,
    "last_run_at": "2026-05-08T00:14:30.865324Z",
    "last_success_at": "2026-05-08T00:14:30.865324Z",
    "last_error": null,
    "stale": false
  },
  {
    "source_name": "Google News SEA Hobby Conventions",
    "status": "ok",
    "fetched_count": 12,
    "persisted_count": 12,
    "error_count": 0,
    "consecutive_failures": 0,
    "last_run_at": "2026-05-08T00:14:30.883911Z",
    "last_success_at": "2026-05-08T00:14:30.883911Z",
    "last_error": null,
    "stale": false
  },
  {
    "source_name": "Google News SEA Rhythm Games",
    "status": "ok",
    "fetched_count": 0,
    "persisted_count": 0,
    "error_count": 0,
    "consecutive_failures": 0,
    "last_run_at": "2026-05-08T00:14:30.870866Z",
    "last_success_at": "2026-05-08T00:14:30.870866Z",
    "last_error": null,
    "stale": false
  },
  {
    "source_name": "Google News SEA TCG",
    "status": "ok",
    "fetched_count": 7,
    "persisted_count": 7,
    "error_count": 0,
    "consecutive_failures": 0,
    "last_run_at": "2026-05-08T00:14:30.845479Z",
    "last_success_at": "2026-05-08T00:14:30.845479Z",
    "last_error": null,
    "stale": false
  },
  {
    "source_name": "Google News SEA Tokusatsu",
    "status": "ok",
    "fetched_count": 4,
    "persisted_count": 4,
    "error_count": 0,
    "consecutive_failures": 0,
    "last_run_at": "2026-05-08T00:14:30.876892Z",
    "last_success_at": "2026-05-08T00:14:30.876892Z",
    "last_error": null,
    "stale": false
  },
  {
    "source_name": "Google News SEA Visual Novels",
    "status": "ok",
    "fetched_count": 10,
    "persisted_count": 10,
    "error_count": 0,
    "consecutive_failures": 0,
    "last_run_at": "2026-05-08T00:14:30.858745Z",
    "last_success_at": "2026-05-08T00:14:30.858745Z",
    "last_error": null,
    "stale": false
  },
  {
    "source_name": "Google News SEA VTuber Concerts",
    "status": "ok",
    "fetched_count": 11,
    "persisted_count": 10,
    "error_count": 0,
    "consecutive_failures": 0,
    "last_run_at": "2026-05-08T00:14:30.878181Z",
    "last_success_at": "2026-05-08T00:14:30.878181Z",
    "last_error": null,
    "stale": false
  },
  {
    "source_name": "Google News SEA VTuber Merch Collabs",
    "status": "ok",
    "fetched_count": 12,
    "persisted_count": 8,
    "error_count": 0,
    "consecutive_failures": 0,
    "last_run_at": "2026-05-08T00:14:30.887801Z",
    "last_success_at": "2026-05-08T00:14:30.887801Z",
    "last_error": null,
    "stale": false
  },
  {
    "source_name": "Google News SEA VTubers",
    "status": "ok",
    "fetched_count": 8,
    "persisted_count": 8,
    "error_count": 0,
    "consecutive_failures": 0,
    "last_run_at": "2026-05-08T00:14:30.849753Z",
    "last_success_at": "2026-05-08T00:14:30.849753Z",
    "last_error": null,
    "stale": false
  },
  {
    "source_name": "Google News SG ACG",
    "status": "ok",
    "fetched_count": 8,
    "persisted_count": 8,
    "error_count": 0,
    "consecutive_failures": 0,
    "last_run_at": "2026-05-08T00:14:30.811887Z",
    "last_success_at": "2026-05-08T00:14:30.811887Z",
    "last_error": null,
    "stale": false
  },
  {
    "source_name": "Google News SG Anisong",
    "status": "ok",
    "fetched_count": 4,
    "persisted_count": 2,
    "error_count": 0,
    "consecutive_failures": 0,
    "last_run_at": "2026-05-08T00:14:30.858001Z",
    "last_success_at": "2026-05-08T00:14:30.858001Z",
    "last_error": null,
    "stale": false
  },
  {
    "source_name": "Google News SG Collab Cafes",
    "status": "ok",
    "fetched_count": 10,
    "persisted_count": 10,
    "error_count": 0,
    "consecutive_failures": 0,
    "last_run_at": "2026-05-08T00:14:30.861978Z",
    "last_success_at": "2026-05-08T00:14:30.861978Z",
    "last_error": null,
    "stale": false
  },
  {
    "source_name": "Google News SG Convention Guests",
    "status": "ok",
    "fetched_count": 7,
    "persisted_count": 7,
    "error_count": 0,
    "consecutive_failures": 0,
    "last_run_at": "2026-05-08T00:14:30.874295Z",
    "last_success_at": "2026-05-08T00:14:30.874295Z",
    "last_error": null,
    "stale": false
  },
  {
    "source_name": "Google News SG Cosplay",
    "status": "ok",
    "fetched_count": 9,
    "persisted_count": 6,
    "error_count": 0,
    "consecutive_failures": 0,
    "last_run_at": "2026-05-08T00:14:30.847953Z",
    "last_success_at": "2026-05-08T00:14:30.847953Z",
    "last_error": null,
    "stale": false
  },
  {
    "source_name": "Google News SG Creator Hubs",
    "status": "ok",
    "fetched_count": 0,
    "persisted_count": 0,
    "error_count": 0,
    "consecutive_failures": 0,
    "last_run_at": "2026-05-08T00:14:30.876267Z",
    "last_success_at": "2026-05-08T00:14:30.876267Z",
    "last_error": null,
    "stale": false
  },
  {
    "source_name": "Google News SG Doujin Markets",
    "status": "ok",
    "fetched_count": 3,
    "persisted_count": 2,
    "error_count": 0,
    "consecutive_failures": 0,
    "last_run_at": "2026-05-08T00:14:30.870868Z",
    "last_success_at": "2026-05-08T00:14:30.870868Z",
    "last_error": null,
    "stale": false
  },
  {
    "source_name": "Google News SG Events",
    "status": "ok",
    "fetched_count": 12,
    "persisted_count": 11,
    "error_count": 0,
    "consecutive_failures": 0,
    "last_run_at": "2026-05-08T00:14:30.814551Z",
    "last_success_at": "2026-05-08T00:14:30.814551Z",
    "last_error": null,
    "stale": false
  },
  {
    "source_name": "Google News SG Figures",
    "status": "ok",
    "fetched_count": 11,
    "persisted_count": 11,
    "error_count": 0,
    "consecutive_failures": 0,
    "last_run_at": "2026-05-08T00:14:30.852719Z",
    "last_success_at": "2026-05-08T00:14:30.852719Z",
    "last_error": null,
    "stale": false
  },
  {
    "source_name": "Google News SG Pop-Up Stores",
    "status": "ok",
    "fetched_count": 5,
    "persisted_count": 4,
    "error_count": 0,
    "consecutive_failures": 0,
    "last_run_at": "2026-05-08T00:14:30.869282Z",
    "last_success_at": "2026-05-08T00:14:30.869282Z",
    "last_error": null,
    "stale": false
  },
  {
    "source_name": "Honey's Anime",
    "status": "ok",
    "fetched_count": 11,
    "persisted_count": 11,
    "error_count": 0,
    "consecutive_failures": 0,
    "last_run_at": "2026-05-08T00:14:30.689843Z",
    "last_success_at": "2026-05-08T00:14:30.689843Z",
    "last_error": null,
    "stale": false
  },
  {
    "source_name": "J-List Blog",
    "status": "ok",
    "fetched_count": 1,
    "persisted_count": 1,
    "error_count": 0,
    "consecutive_failures": 0,
    "last_run_at": "2026-05-08T00:14:30.803327Z",
    "last_success_at": "2026-05-08T00:14:30.803327Z",
    "last_error": null,
    "stale": false
  },
  {
    "source_name": "MonsterVine",
    "status": "ok",
    "fetched_count": 2,
    "persisted_count": 2,
    "error_count": 0,
    "consecutive_failures": 0,
    "last_run_at": "2026-05-08T00:14:30.802216Z",
    "last_success_at": "2026-05-08T00:14:30.802216Z",
    "last_error": null,
    "stale": false
  },
  {
    "source_name": "Niche Gamer",
    "status": "ok",
    "fetched_count": 3,
    "persisted_count": 3,
    "error_count": 0,
    "consecutive_failures": 0,
    "last_run_at": "2026-05-08T00:14:30.753536Z",
    "last_success_at": "2026-05-08T00:14:30.753536Z",
    "last_error": null,
    "stale": false
  },
  {
    "source_name": "Nintendo Everything",
    "status": "ok",
    "fetched_count": 1,
    "persisted_count": 1,
    "error_count": 0,
    "consecutive_failures": 0,
    "last_run_at": "2026-05-08T00:14:30.728918Z",
    "last_success_at": "2026-05-08T00:14:30.728918Z",
    "last_error": null,
    "stale": false
  },
  {
    "source_name": "Noisy Pixel",
    "status": "ok",
    "fetched_count": 2,
    "persisted_count": 2,
    "error_count": 0,
    "consecutive_failures": 0,
    "last_run_at": "2026-05-08T00:14:30.727844Z",
    "last_success_at": "2026-05-08T00:14:30.727844Z",
    "last_error": null,
    "stale": false
  },
  {
    "source_name": "NookGaming",
    "status": "error",
    "fetched_count": 0,
    "persisted_count": 0,
    "error_count": 1,
    "consecutive_failures": 1,
    "last_run_at": "2026-05-08T00:14:30.729558Z",
    "last_success_at": null,
    "last_error": "Client error '403 Forbidden' for url 'https://www.nookgaming.com/feed/' For more information check: https://developer.mozilla.org/en-US/docs/Web/HTTP/Status/403",
    "stale": false
  },
  {
    "source_name": "Operation Rainfall",
    "status": "error",
    "fetched_count": 0,
    "persisted_count": 0,
    "error_count": 1,
    "consecutive_failures": 1,
    "last_run_at": "2026-05-08T00:14:30.788370Z",
    "last_success_at": null,
    "last_error": "Client error '403 Forbidden' for url 'https://operationrainfall.com/feed/' For more information check: https://developer.mozilla.org/en-US/docs/Web/HTTP/Status/403",
    "stale": false
  },
  {
    "source_name": "Otaku USA",
    "status": "ok",
    "fetched_count": 10,
    "persisted_count": 10,
    "error_count": 0,
    "consecutive_failures": 0,
    "last_run_at": "2026-05-08T00:14:30.759640Z",
    "last_success_at": "2026-05-08T00:14:30.759640Z",
    "last_error": null,
    "stale": false
  },
  {
    "source_name": "Rice Digital",
    "status": "ok",
    "fetched_count": 2,
    "persisted_count": 2,
    "error_count": 0,
    "consecutive_failures": 0,
    "last_run_at": "2026-05-08T00:14:30.801085Z",
    "last_success_at": "2026-05-08T00:14:30.801085Z",
    "last_error": null,
    "stale": false
  },
  {
    "source_name": "RPG Site",
    "status": "ok",
    "fetched_count": 6,
    "persisted_count": 6,
    "error_count": 0,
    "consecutive_failures": 0,
    "last_run_at": "2026-05-08T00:14:30.723063Z",
    "last_success_at": "2026-05-08T00:14:30.723063Z",
    "last_error": null,
    "stale": false
  },
  {
    "source_name": "RPGamer",
    "status": "ok",
    "fetched_count": 12,
    "persisted_count": 12,
    "error_count": 0,
    "consecutive_failures": 0,
    "last_run_at": "2026-05-08T00:14:30.731516Z",
    "last_success_at": "2026-05-08T00:14:30.731516Z",
    "last_error": null,
    "stale": false
  },
  {
    "source_name": "SEA Merch News Pages",
    "status": "ok",
    "fetched_count": 6,
    "persisted_count": 6,
    "error_count": 0,
    "consecutive_failures": 0,
    "last_run_at": "2026-05-08T00:14:30.679072Z",
    "last_success_at": "2026-05-08T00:14:30.679072Z",
    "last_error": null,
    "stale": false
  },
  {
    "source_name": "SEA Official Event Pages",
    "status": "ok",
    "fetched_count": 4,
    "persisted_count": 4,
    "error_count": 0,
    "consecutive_failures": 0,
    "last_run_at": "2026-05-08T00:14:30.681433Z",
    "last_success_at": "2026-05-08T00:14:30.681433Z",
    "last_error": null,
    "stale": false
  },
  {
    "source_name": "SG Source Pages",
    "status": "ok",
    "fetched_count": 12,
    "persisted_count": 12,
    "error_count": 0,
    "consecutive_failures": 0,
    "last_run_at": "2026-05-08T00:14:30.673899Z",
    "last_success_at": "2026-05-08T00:14:30.673899Z",
    "last_error": null,
    "stale": false
  },
  {
    "source_name": "Siliconera",
    "status": "ok",
    "fetched_count": 12,
    "persisted_count": 12,
    "error_count": 0,
    "consecutive_failures": 0,
    "last_run_at": "2026-05-08T00:14:30.683156Z",
    "last_success_at": "2026-05-08T00:14:30.683156Z",
    "last_error": null,
    "stale": false
  },
  {
    "source_name": "Tokyo Otaku Mode",
    "status": "ok",
    "fetched_count": 9,
    "persisted_count": 9,
    "error_count": 0,
    "consecutive_failures": 0,
    "last_run_at": "2026-05-08T00:14:30.767971Z",
    "last_success_at": "2026-05-08T00:14:30.767971Z",
    "last_error": null,
    "stale": false
  }
]