[
  {
    "id": "548beb1e8f268730a2e198bb4a33428111d5cce5",
    "title": "Singapore Cements Esports Hub Status with BLAST Premier Open 2027 - BriefGlance",
    "url": "https://briefglance.com/articles/singapore-cements-esports-hub-status-with-blast-premier-open-2027",
    "source_name": "Google News SEA Esports",
    "source_type": "rss",
    "published_at": "2026-05-19T10:35:21Z",
    "summary": "Singapore Cements Esports Hub Status with BLAST Premier Open 2027 BriefGlance",
    "content": "",
    "categories": [
      "esports",
      "games"
    ],
    "tags": [
      "singapore"
    ],
    "entity_tags": [],
    "region_tags": [
      "Singapore",
      "SEA"
    ],
    "sg_relevance": 0.43,
    "freshness_score": 0.9683426458607365,
    "home_score": 0.7953,
    "source_quality": 0.76,
    "image_url": null,
    "event_metadata": null,
    "result_type": "article"
  },
  {
    "id": "743d7daef80801dd541f3ffbcae26d4204ee5073",
    "title": "BIGBANG's TAEYANG unveils 'QUINTESSENCE', his first solo album in 9 years along with 'LIVE FAST DIE SLOW' MV",
    "url": "https://www.bandwagon.asia/articles/bigbang-s-taeyang-unveils-quintessence-his-first-solo-album-in-9-years-listen",
    "source_name": "Bandwagon Asia",
    "source_type": "rss",
    "published_at": "2026-05-19T08:30:00Z",
    "summary": "Amidst a monumental year for BIGBANG as they have their exciting 20th anniversary tour just on the horizon, TAEYANG sets another milestone in his solo artistry, releasing his album",
    "content": "",
    "categories": [
      "games",
      "esports",
      "anime",
      "events",
      "merch"
    ],
    "tags": [
      "idol",
      "jrpg"
    ],
    "entity_tags": [],
    "region_tags": [
      "Singapore",
      "SEA"
    ],
    "sg_relevance": 0.43,
    "freshness_score": 0.9406493112239487,
    "home_score": 0.7813,
    "source_quality": 0.67,
    "image_url": "https://cdn.filestackcontent.com/crop=d:%5B0%2C89%2C1080%2C540%5D/resize=w:1920/pjpg=q:90/compress/3zawckoRCShW8M40UWbt",
    "event_metadata": {
      "event_type": "convention",
      "date_label": null,
      "venue": null,
      "ticket_status": null,
      "ticket_url": null,
      "guest_status": null,
      "guest_names": [],
      "merch_status": null
    },
    "result_type": "article"
  },
  {
    "id": "925a76aa58477c018b2a3b3c4198c42e5eaa88fe",
    "title": "BLEACH: TYBW Part 4 (Final Season) Reveals New Trailer",
    "url": "https://animecorner.me/bleach-tybw-part-4-final-season-reveals-new-trailer/",
    "source_name": "Anime Corner",
    "source_type": "rss",
    "published_at": "2026-05-19T11:48:29Z",
    "summary": "The final season of BLEACH: TYBW Part 4, titled Bleach: Thousand-Year Blood War Final\u2026",
    "content": "",
    "categories": [
      "anime",
      "manga",
      "events",
      "games"
    ],
    "tags": [],
    "entity_tags": [],
    "region_tags": [
      "SEA"
    ],
    "sg_relevance": 0.08,
    "freshness_score": 0.9848755489528394,
    "home_score": 0.7332,
    "source_quality": 0.8,
    "image_url": null,
    "event_metadata": null,
    "result_type": "article"
  },
  {
    "id": "0ec0f8f6263028126ec718745bb756c70f105c6b",
    "title": "Mushoku Tensei Season 3 Unveils New Key Visual",
    "url": "https://animecorner.me/mushoku-tensei-season-3-unveils-new-key-visual/",
    "source_name": "Anime Corner",
    "source_type": "rss",
    "published_at": "2026-05-19T10:52:49Z",
    "summary": "The upcoming Mushoku Tensei: Jobless Reincarnation Season 3 unveiled a new key visual on Tuesday",
    "content": "",
    "categories": [
      "anime",
      "manga",
      "events",
      "games"
    ],
    "tags": [],
    "entity_tags": [],
    "region_tags": [
      "SEA"
    ],
    "sg_relevance": 0.08,
    "freshness_score": 0.9722660520560641,
    "home_score": 0.7275,
    "source_quality": 0.8,
    "image_url": null,
    "event_metadata": null,
    "result_type": "article"
  },
  {
    "id": "de1054a0fefe8d3f0cf93190df1af9e76f52d146",
    "title": "Mushoku Tensei: Jobless Reincarnation Season 3 Anime Unveils New Key Visual",
    "url": "https://crunchyroll.com/news/latest/2026/5/19/mushoku-tensei-jobless-reincarnation-season-3-anime-key-visual",
    "source_name": "Crunchyroll News",
    "source_type": "rss",
    "published_at": "2026-05-19T10:47:00Z",
    "summary": "Mushoku Tensei: Jobless Reincarnation Season 3 Anime Unveils New Key Visual",
    "content": "",
    "categories": [
      "anime",
      "manga",
      "games",
      "events"
    ],
    "tags": [],
    "entity_tags": [],
    "region_tags": [
      "SEA"
    ],
    "sg_relevance": 0.08,
    "freshness_score": 0.9709577877904094,
    "home_score": 0.7254,
    "source_quality": 0.79,
    "image_url": null,
    "event_metadata": {
      "event_type": null,
      "date_label": "July 5",
      "venue": null,
      "ticket_status": null,
      "ticket_url": null,
      "guest_status": null,
      "guest_names": [],
      "merch_status": null
    },
    "result_type": "article"
  },
  {
    "id": "a8c5953666f3cd34861a536979a3c54f1e0b6b28",
    "title": "Mushoku Tensei Season 3 Unveils Key Visual",
    "url": "https://anitrendz.net/news/2026/05/19/mushoku-tensei-season-3-unveils-key-visual/?utm_source=rss&utm_medium=rss&utm_campaign=mushoku-tensei-season-3-unveils-key-visual",
    "source_name": "Anime Trending",
    "source_type": "rss",
    "published_at": "2026-05-19T10:44:39Z",
    "summary": "A key visual for the upcoming Mushoku Tensei: Jobless Reincarnation Season 3 has been released",
    "content": "",
    "categories": [
      "anime",
      "manga",
      "events",
      "games"
    ],
    "tags": [],
    "entity_tags": [],
    "region_tags": [
      "SEA"
    ],
    "sg_relevance": 0.08,
    "freshness_score": 0.9704296410081329,
    "home_score": 0.7237,
    "source_quality": 0.78,
    "image_url": null,
    "event_metadata": null,
    "result_type": "article"
  },
  {
    "id": "8962c1653f6b67fcfe2c904e0445bc3ae7d66259",
    "title": "Japan Could Lose 400 Anime Episodes Worth Of Production By 2030, Animator Supporters Warns",
    "url": "https://animehunch.com/japan-could-lose-400-anime-episodes-worth-of-production-by-2030-animator-supporters-warns/",
    "source_name": "Anime Hunch",
    "source_type": "rss",
    "published_at": "2026-05-19T08:56:15Z",
    "summary": "Japan\u2019s anime industry could face a dramatic production decline by 2030 due to worsening labor shortages and poor working conditions, according to Jun Sugawara from the nonprofit o",
    "content": "",
    "categories": [
      "anime",
      "manga",
      "events"
    ],
    "tags": [],
    "entity_tags": [],
    "region_tags": [
      "SEA"
    ],
    "sg_relevance": 0.08,
    "freshness_score": 0.9463820420646676,
    "home_score": 0.7129,
    "source_quality": 0.78,
    "image_url": null,
    "event_metadata": null,
    "result_type": "article"
  },
  {
    "id": "b4bcf96b39f96fbd2ad6c9a381be1363f27a975f",
    "title": "Steam updates game tags: Removes NSFW, RPGMaker, adds \u201cBullet Heaven\u201d",
    "url": "https://esports.gg/news/gaming/steam-game-tag-update-2026/",
    "source_name": "Esports.gg",
    "source_type": "rss",
    "published_at": "2026-05-19T11:03:14Z",
    "summary": "Steam is removing the \"NSFW\" and \"Mature\" tags (among many) from its storefront, in favor of 17 new ones including \"Bullet Heaven,\" \"Capybaras,\" and \"Wolves",
    "content": "",
    "categories": [
      "esports",
      "games",
      "merch"
    ],
    "tags": [],
    "entity_tags": [],
    "region_tags": [
      "SEA"
    ],
    "sg_relevance": 0.08,
    "freshness_score": 0.9746131649535748,
    "home_score": 0.7106,
    "source_quality": 0.76,
    "image_url": "https://cdn.esports.gg/wp-content/uploads/2021/02/13122740/cropped-esports-gg-favicon-1-32x32.png",
    "event_metadata": null,
    "result_type": "article"
  },
  {
    "id": "9b78377dd1f8f33bf0d9fc2e9ef6fef7a9532c0c",
    "title": "Final Fantasy 14 Limited-Time Free Download Officially Confirmed - ScreenRant",
    "url": "https://screenrant.com/final-fantasy-14-may-2026-free-download/",
    "source_name": "Google News JRPG",
    "source_type": "rss",
    "published_at": "2026-05-19T12:18:57Z",
    "summary": "Final Fantasy 14 Limited-Time Free Download Officially Confirmed ScreenRant",
    "content": "",
    "categories": [
      "games",
      "events"
    ],
    "tags": [],
    "entity_tags": [
      "Final Fantasy"
    ],
    "region_tags": [],
    "sg_relevance": 0.0,
    "freshness_score": 0.9918456554303838,
    "home_score": 0.7103,
    "source_quality": 0.76,
    "image_url": null,
    "event_metadata": null,
    "result_type": "article"
  },
  {
    "id": "4cbbd077931cc00822a7f4942bca55257ef3b1f9",
    "title": "Bleach: Thousand-Year Blood War Final Part - The Calamity Anime Fights to the End in New Trailer",
    "url": "https://crunchyroll.com/news/latest/2026/5/19/bleach-thousand-year-blood-war-final-part-the-calamity-anime-main-trailer",
    "source_name": "Crunchyroll News",
    "source_type": "rss",
    "published_at": "2026-05-19T11:12:00Z",
    "summary": "Bleach: Thousand-Year Blood War Final Part - The Calamity Anime Fights to the End in New Trailer",
    "content": "",
    "categories": [
      "anime",
      "manga",
      "games",
      "events"
    ],
    "tags": [],
    "entity_tags": [],
    "region_tags": [],
    "sg_relevance": 0.0,
    "freshness_score": 0.9765930475607676,
    "home_score": 0.708,
    "source_quality": 0.79,
    "image_url": null,
    "event_metadata": null,
    "result_type": "article"
  },
  {
    "id": "53484a0cd8a6071f6ebb6ce8b03d8b416aae4c14",
    "title": "Bleach: Thousand-Year Blood War Part 4 \u2013 The Calamity\u2019s Main Trailer Teases Multiple Showdowns",
    "url": "https://anitrendz.net/news/2026/05/19/bleach-thousand-year-blood-war-part-4-the-calamitys-main-trailer-teases-multiple-showdowns/?utm_source=rss&utm_medium=rss&utm_campaign=bleach-thousand-year-blood-war-part-4-the-calamitys-main-trailer-teases-multiple-showdowns",
    "source_name": "Anime Trending",
    "source_type": "rss",
    "published_at": "2026-05-19T11:16:11Z",
    "summary": "A main trailer for Bleach: Thousand-Year Blood War Part 4 \u2013 The Calamity has been released",
    "content": "",
    "categories": [
      "anime",
      "manga",
      "events",
      "games"
    ],
    "tags": [],
    "entity_tags": [],
    "region_tags": [],
    "sg_relevance": 0.0,
    "freshness_score": 0.9775390955329503,
    "home_score": 0.7069,
    "source_quality": 0.78,
    "image_url": null,
    "event_metadata": null,
    "result_type": "article"
  },
  {
    "id": "86562d2d5f88daf7cba008c56a2746e115a28d36",
    "title": "Street Fighter 6\u2019s new Random Avatar Matches and Avatar Arcade explained",
    "url": "https://esports.gg/guides/street-fighter-6/random-avatar-match-avatar-arcade/",
    "source_name": "Esports.gg",
    "source_type": "rss",
    "published_at": "2026-05-19T08:49:04Z",
    "summary": "Here's everything you need to know about Street Fighter 6's new modes: Random Avatar Match and Avatar Arcade!",
    "content": "",
    "categories": [
      "esports",
      "games"
    ],
    "tags": [],
    "entity_tags": [
      "Street Fighter 6"
    ],
    "region_tags": [
      "SEA"
    ],
    "sg_relevance": 0.08,
    "freshness_score": 0.944809705881315,
    "home_score": 0.6972,
    "source_quality": 0.76,
    "image_url": "https://cdn.esports.gg/wp-content/uploads/2021/02/13122740/cropped-esports-gg-favicon-1-32x32.png",
    "event_metadata": null,
    "result_type": "article"
  },
  {
    "id": "56b66715f655f72a86c05dafd32b32cdca8b55a6",
    "title": "NovaFlare reveals Project Rabbit as a new Action RPG coming to PC via Steam",
    "url": "https://www.rpgsite.net/news/20393-novaflare-reveals-project-rabbit-as-new-action-rpg-coming-to-pc-via-steam",
    "source_name": "RPG Site",
    "source_type": "rss",
    "published_at": "2026-05-19T12:37:49Z",
    "summary": "This South Korean Souls-like high-difficulty game is being themed after Alice in Wonderland",
    "content": "",
    "categories": [
      "games",
      "anime"
    ],
    "tags": [],
    "entity_tags": [],
    "region_tags": [],
    "sg_relevance": 0.0,
    "freshness_score": 0.9961872048674392,
    "home_score": 0.6958,
    "source_quality": 0.81,
    "image_url": null,
    "event_metadata": null,
    "result_type": "article"
  },
  {
    "id": "3b456b9794fb71208fce8c03459c928275bbd8d4",
    "title": "Junji Ito\u2019s The Long Hair in the Attic Gets Live-Action Film from Thai Director Sitisiri Mongkolsiri",
    "url": "https://anitrendz.net/news/2026/05/19/junji-itos-the-long-hair-in-the-attic-gets-live-action-film-from-thai-director-sitisiri-mongkolsiri/?utm_source=rss&utm_medium=rss&utm_campaign=junji-itos-the-long-hair-in-the-attic-gets-live-action-film-from-thai-director-sitisiri-mongkolsiri",
    "source_name": "Anime Trending",
    "source_type": "rss",
    "published_at": "2026-05-19T07:34:50Z",
    "summary": "A live-action film adaptation of Junji Ito's The Long Hair in the Attic is planned to begin filming in 2027",
    "content": "",
    "categories": [
      "anime",
      "manga",
      "events",
      "games"
    ],
    "tags": [],
    "entity_tags": [],
    "region_tags": [],
    "sg_relevance": 0.0,
    "freshness_score": 0.9287130938339101,
    "home_score": 0.6849,
    "source_quality": 0.78,
    "image_url": null,
    "event_metadata": null,
    "result_type": "article"
  },
  {
    "id": "81122c22447e1e9136b7a0c5ca1f39a63f54ec7c",
    "title": "Best PS5 And PS4 Turn-Based RPG Deals This Week - Turn Based Lovers",
    "url": "https://turnbasedlovers.com/news/best-ps5-and-ps4-turn-based-rpg-deals-this-week/",
    "source_name": "Google News JRPG",
    "source_type": "rss",
    "published_at": "2026-05-19T11:37:15Z",
    "summary": "Best PS5 And PS4 Turn-Based RPG Deals This Week Turn Based Lovers",
    "content": "",
    "categories": [
      "games"
    ],
    "tags": [
      "jrpg"
    ],
    "entity_tags": [],
    "region_tags": [],
    "sg_relevance": 0.0,
    "freshness_score": 0.9823176507013991,
    "home_score": 0.682,
    "source_quality": 0.76,
    "image_url": null,
    "event_metadata": null,
    "result_type": "article"
  },
  {
    "id": "fc522b8ad8f70a90dd01853e0eb7799f92387962",
    "title": "Paul Feig to helm the adaptation of Persona - Cinema Express",
    "url": "https://www.cinemaexpress.com/english/news/2026/May/19/paul-feig-to-helm-the-adaptation-of-persona",
    "source_name": "Google News JRPG",
    "source_type": "rss",
    "published_at": "2026-05-19T11:22:45Z",
    "summary": "Paul Feig to helm the adaptation of Persona Cinema Express",
    "content": "",
    "categories": [
      "games"
    ],
    "tags": [
      "jrpg"
    ],
    "entity_tags": [],
    "region_tags": [],
    "sg_relevance": 0.0,
    "freshness_score": 0.9790260427671607,
    "home_score": 0.6806,
    "source_quality": 0.76,
    "image_url": null,
    "event_metadata": null,
    "result_type": "article"
  },
  {
    "id": "64ef00a34dec078ed7e815fdf1e5482c28f46554",
    "title": "Japanese publisher\u2019s site temporarily crashes from sheer number of people flocking to download NSFW patch for sexy nun action JRPG SiNiSiStar2",
    "url": "https://automaton-media.com/en/news/japanese-publishers-site-temporarily-crashes-from-sheer-number-of-people-flocking-to-download-nsfw-patch-for-sexy-nun-action-jrpg-sinisistar2/",
    "source_name": "Automaton West",
    "source_type": "rss",
    "published_at": "2026-05-19T09:08:08Z",
    "summary": "Japanese gothic action RPG SiNiSiStar2 just released on Steam, alongside a special 18+ patch that unlocks the game's mature scenes",
    "content": "",
    "categories": [
      "games",
      "anime",
      "merch"
    ],
    "tags": [
      "jrpg"
    ],
    "entity_tags": [],
    "region_tags": [],
    "sg_relevance": 0.0,
    "freshness_score": 0.9489891621907295,
    "home_score": 0.6775,
    "source_quality": 0.79,
    "image_url": null,
    "event_metadata": null,
    "result_type": "article"
  },
  {
    "id": "2d4a4445ba23d4edc609ebaa9859e128c1a929e8",
    "title": "Crunchyroll\u2019s Profits Declined By Over 63% In 2025",
    "url": "https://animehunch.com/crunchyrolls-profits-declined-by-over-63-in-2025/",
    "source_name": "Anime Hunch",
    "source_type": "rss",
    "published_at": "2026-05-19T11:20:54Z",
    "summary": "Crunchyroll\u2019s financial results for the fiscal year ending in December 2025 revealed a 63",
    "content": "",
    "categories": [
      "anime",
      "manga"
    ],
    "tags": [],
    "entity_tags": [],
    "region_tags": [],
    "sg_relevance": 0.0,
    "freshness_score": 0.9786070042562074,
    "home_score": 0.6774,
    "source_quality": 0.78,
    "image_url": null,
    "event_metadata": {
      "event_type": null,
      "date_label": "May 19, 2026",
      "venue": null,
      "ticket_status": null,
      "ticket_url": null,
      "guest_status": null,
      "guest_names": [],
      "merch_status": null
    },
    "result_type": "article"
  },
  {
    "id": "6bdb6df4b8cfbb8f7931e58ba9bc130f8422933e",
    "title": "Gigabyte\u2019s showcases the Aorus Elite-P Ice, as anime\u2019s influence in PC components grows - HardwareZone",
    "url": "https://www.hardwarezone.com.sg/pc/components/gigabyte-aorus-elite-p-ice-anime-pc-gaming-motherboard",
    "source_name": "Google News SG ACG",
    "source_type": "rss",
    "published_at": "2026-05-18T09:49:50Z",
    "summary": "Gigabyte\u2019s showcases the Aorus Elite-P Ice, as anime\u2019s influence in PC components grows HardwareZone",
    "content": "",
    "categories": [
      "events",
      "games",
      "anime"
    ],
    "tags": [],
    "entity_tags": [],
    "region_tags": [
      "Singapore",
      "SEA"
    ],
    "sg_relevance": 0.43,
    "freshness_score": 0.6865756769075966,
    "home_score": 0.6745,
    "source_quality": 0.72,
    "image_url": null,
    "event_metadata": null,
    "result_type": "article"
  },
  {
    "id": "e65ded4dad0f1b101ab0e9638d2b19d442b78695",
    "title": "Final Fantasy creator Hironobu Sakaguchi responds to the backlash after shouting out a Final Fantasy 6 AI mock-up goes viral for all the wrong reasons - GamesRadar+",
    "url": "https://www.gamesradar.com/games/final-fantasy/final-fantasy-creator-hironobu-sakaguchi-responds-to-the-backlash-after-shouting-out-a-final-fantasy-6-ai-mock-up-goes-viral-for-all-the-wrong-reasons/",
    "source_name": "Google News JRPG",
    "source_type": "rss",
    "published_at": "2026-05-19T10:17:57Z",
    "summary": "Final Fantasy creator Hironobu Sakaguchi responds to the backlash after shouting out a Final Fantasy 6 AI mock-up goes viral for all the wrong reasons GamesRadar+",
    "content": "",
    "categories": [
      "games"
    ],
    "tags": [],
    "entity_tags": [
      "Final Fantasy"
    ],
    "region_tags": [],
    "sg_relevance": 0.0,
    "freshness_score": 0.9644502455308483,
    "home_score": 0.674,
    "source_quality": 0.76,
    "image_url": null,
    "event_metadata": null,
    "result_type": "article"
  },
  {
    "id": "4c4d86106ef8cbf1a5518126ca72dc86c43ac5cf",
    "title": "Kimi to Hanabi to Yakusoku to Reveals Main Trailer and Visual, Casts Rie Takahashi",
    "url": "https://anitrendz.net/news/2026/05/18/kimi-to-hanabi-to-yakusoku-to-reveals-main-trailer-and-visual-casts-rie-takahashi/?utm_source=rss&utm_medium=rss&utm_campaign=kimi-to-hanabi-to-yakusoku-to-reveals-main-trailer-and-visual-casts-rie-takahashi",
    "source_name": "Anime Trending",
    "source_type": "rss",
    "published_at": "2026-05-19T05:19:08Z",
    "summary": "The Kimi to Hanabi to Yakusoku to anime film has gotten a main trailer and main visual",
    "content": "",
    "categories": [
      "anime",
      "manga",
      "events"
    ],
    "tags": [],
    "entity_tags": [],
    "region_tags": [],
    "sg_relevance": 0.0,
    "freshness_score": 0.8999937503081875,
    "home_score": 0.672,
    "source_quality": 0.78,
    "image_url": null,
    "event_metadata": null,
    "result_type": "article"
  },
  {
    "id": "80282a1eb8280721f99070e9abc532ee1d0bda08",
    "title": "Esports orgs need to take pros\u2019 physical health more seriously as they continue to retire from wrist and hand injuries",
    "url": "https://esportsinsider.com/2026/05/esports-wrist-and-hand-injuries",
    "source_name": "Esports Insider",
    "source_type": "rss",
    "published_at": "2026-05-19T00:51:05Z",
    "summary": "I recently saw a post from Street Fighter 6 pro Kakeru Watanabe that announced he\u2019d developed tendonitis",
    "content": "",
    "categories": [
      "esports",
      "games",
      "events"
    ],
    "tags": [],
    "entity_tags": [
      "Street Fighter 6"
    ],
    "region_tags": [
      "SEA"
    ],
    "sg_relevance": 0.08,
    "freshness_score": 0.8458475778955743,
    "home_score": 0.6661,
    "source_quality": 0.77,
    "image_url": null,
    "event_metadata": null,
    "result_type": "article"
  },
  {
    "id": "ec62461990c462e62599130686a848a6d417d5ed",
    "title": "Nintendo Preparing WarioWare-like Pictonico Mobile Game",
    "url": "https://www.siliconera.com/nintendo-preparing-warioware-like-pictonico-mobile-game/",
    "source_name": "Siliconera",
    "source_type": "rss",
    "published_at": "2026-05-19T02:30:00Z",
    "summary": "Pictonico, a WarioWare like game from Nintendo that involves photos, is heading to mobile devices",
    "content": "",
    "categories": [
      "games",
      "anime",
      "merch",
      "events"
    ],
    "tags": [],
    "entity_tags": [],
    "region_tags": [],
    "sg_relevance": 0.0,
    "freshness_score": 0.8654391638747065,
    "home_score": 0.6624,
    "source_quality": 0.82,
    "image_url": null,
    "event_metadata": null,
    "result_type": "article"
  },
  {
    "id": "b761b3dfe520340db78054185a31911eda3bdb6f",
    "title": "Final Fantasy XI Server Replacements, Story Teased",
    "url": "https://www.siliconera.com/final-fantasy-xi-server-replacements-story-teased/",
    "source_name": "Siliconera",
    "source_type": "rss",
    "published_at": "2026-05-19T02:00:00Z",
    "summary": "To continue Final Fantasy XI support, Yoji Fujito discussed the server replacement and possible new additions",
    "content": "",
    "categories": [
      "games",
      "anime",
      "merch",
      "events"
    ],
    "tags": [],
    "entity_tags": [
      "Final Fantasy"
    ],
    "region_tags": [],
    "sg_relevance": 0.0,
    "freshness_score": 0.8594499882412722,
    "home_score": 0.6598,
    "source_quality": 0.82,
    "image_url": null,
    "event_metadata": null,
    "result_type": "article"
  },
  {
    "id": "d824a17d53d8dfb7793b070ca681b8597402c57d",
    "title": "Yokoso Scooby-Doo! Anime Series Announced Featuring Frank Welker and Matthew Lillard",
    "url": "https://crunchyroll.com/news/latest/2026/5/19/yokoso-scooby-doo-anime-series-main-cast-staff",
    "source_name": "Crunchyroll News",
    "source_type": "rss",
    "published_at": "2026-05-19T01:45:00Z",
    "summary": "Yokoso Scooby-Doo! Anime Series Announced Featuring Frank Welker and Matthew Lillard",
    "content": "",
    "categories": [
      "anime",
      "manga",
      "games",
      "events"
    ],
    "tags": [],
    "entity_tags": [],
    "region_tags": [],
    "sg_relevance": 0.0,
    "freshness_score": 0.8564706333743539,
    "home_score": 0.6539,
    "source_quality": 0.79,
    "image_url": null,
    "event_metadata": {
      "event_type": null,
      "date_label": null,
      "venue": null,
      "ticket_status": null,
      "ticket_url": null,
      "guest_status": "Named guests mentioned",
      "guest_names": [
        "Frank Welker"
      ],
      "merch_status": null
    },
    "result_type": "article"
  },
  {
    "id": "7aecf83bcce44ce7d73014ced1b2f3070f1e2369",
    "title": "Kimi to Hanabi to Yakusoku to Anime Film Releases Main Trailer, Visual",
    "url": "https://crunchyroll.com/news/latest/2026/5/19/kimi-to-hanabi-to-yakusoku-to-anime-film-main-trailer-visual",
    "source_name": "Crunchyroll News",
    "source_type": "rss",
    "published_at": "2026-05-19T01:34:00Z",
    "summary": "Timelesz will perform the theme song \"Kienai Hanabi\"",
    "content": "",
    "categories": [
      "anime",
      "manga",
      "games",
      "events"
    ],
    "tags": [],
    "entity_tags": [],
    "region_tags": [],
    "sg_relevance": 0.0,
    "freshness_score": 0.854292578437197,
    "home_score": 0.6529,
    "source_quality": 0.79,
    "image_url": null,
    "event_metadata": null,
    "result_type": "article"
  },
  {
    "id": "82cebb8ab3608763a0995693238c01f3e5a17112",
    "title": "The Adventures of Elliot: The Millennium Tales Demo Now Available on Consoles and PC",
    "url": "https://noisypixel.net/adventures-of-elliot-millennium-tales-demo/",
    "source_name": "Noisy Pixel",
    "source_type": "rss",
    "published_at": "2026-05-19T00:22:58Z",
    "summary": "Square Enix and Claytechworks have announced that the Prologue demo for their upcoming HD-2D action JRPG The Adventures of Elliot: The Millennium Tales is now available on PlayStat",
    "content": "",
    "categories": [
      "games",
      "anime",
      "merch",
      "events"
    ],
    "tags": [
      "jrpg"
    ],
    "entity_tags": [],
    "region_tags": [],
    "sg_relevance": 0.0,
    "freshness_score": 0.8403605404175446,
    "home_score": 0.6452,
    "source_quality": 0.78,
    "image_url": null,
    "event_metadata": null,
    "result_type": "article"
  },
  {
    "id": "6afacfedf29bee50f4bafae53b90ce49a7592b5c",
    "title": "Visual Novel \u2018Enjoy the Diner\u2019 Surpasses 100,000 Sales",
    "url": "https://noisypixel.net/enjoy-the-diner-100000-sales-new-project/",
    "source_name": "Noisy Pixel",
    "source_type": "rss",
    "published_at": "2026-05-18T22:41:47Z",
    "summary": "Developer Monthly Wetland and Studio Dragonet, alongside publisher Waku Waku Games, have announced that their visual novel Enjoy the Diner has surpassed 100,000 copies sold across",
    "content": "",
    "categories": [
      "games",
      "anime",
      "merch",
      "events"
    ],
    "tags": [],
    "entity_tags": [],
    "region_tags": [],
    "sg_relevance": 0.0,
    "freshness_score": 0.8209062757207389,
    "home_score": 0.6364,
    "source_quality": 0.78,
    "image_url": null,
    "event_metadata": null,
    "result_type": "article"
  },
  {
    "id": "2c056779ff54d96fbff5db7ad7a31d0084b22d72",
    "title": "Scooby-Doo! Anime by The Apothecary Diaries, Pokemon Studio OLM Heads to Tubi & Cartoon Network",
    "url": "https://animecorner.me/scooby-doo-anime-olm-heads-to-tubi-cartoon-network/",
    "source_name": "Anime Corner",
    "source_type": "rss",
    "published_at": "2026-05-18T21:49:31Z",
    "summary": "Variety reports that a new anime based on the iconic Scooby-Doo! IP, Yokoso Scooby-Doo!\u2026",
    "content": "",
    "categories": [
      "anime",
      "manga",
      "events"
    ],
    "tags": [],
    "entity_tags": [],
    "region_tags": [],
    "sg_relevance": 0.0,
    "freshness_score": 0.8110340491212764,
    "home_score": 0.635,
    "source_quality": 0.8,
    "image_url": null,
    "event_metadata": null,
    "result_type": "article"
  },
  {
    "id": "66091f399d98471f2e1d23b302e41634b05c0b17",
    "title": "Wuthering Waves Shorekeeper Nendoroid Comes With Butterflies",
    "url": "https://www.siliconera.com/wuthering-waves-shorekeeper-nendoroid-comes-with-butterflies/",
    "source_name": "Siliconera",
    "source_type": "rss",
    "published_at": "2026-05-18T21:00:00Z",
    "summary": "The Shorekeeper Wuthering Waves Nendoroid will come with a few butterflies and an illustration sheet for the figure",
    "content": "",
    "categories": [
      "games",
      "anime",
      "merch",
      "events"
    ],
    "tags": [],
    "entity_tags": [],
    "region_tags": [],
    "sg_relevance": 0.0,
    "freshness_score": 0.8017911722712772,
    "home_score": 0.6338,
    "source_quality": 0.82,
    "image_url": null,
    "event_metadata": null,
    "result_type": "article"
  },
  {
    "id": "9310d631976fde751b0bb5eb2df927c54e91971e",
    "title": "All teams qualified for the VALORANT Masters London 2026",
    "url": "https://esports.gg/news/valorant/teams-qualified-valorant-masters-london-2026/",
    "source_name": "Esports.gg",
    "source_type": "rss",
    "published_at": "2026-05-18T16:53:35Z",
    "summary": "Here are all the teams that have qualified for VALORANT Masters London 2026, set to take place from June 6 to June 21",
    "content": "",
    "categories": [
      "esports",
      "games"
    ],
    "tags": [],
    "entity_tags": [
      "Valorant"
    ],
    "region_tags": [
      "SEA"
    ],
    "sg_relevance": 0.16,
    "freshness_score": 0.7573358686194436,
    "home_score": 0.6328,
    "source_quality": 0.76,
    "image_url": "https://cdn.esports.gg/wp-content/uploads/2021/02/13122740/cropped-esports-gg-favicon-1-32x32.png",
    "event_metadata": {
      "event_type": null,
      "date_label": "June 6",
      "venue": null,
      "ticket_status": null,
      "ticket_url": null,
      "guest_status": null,
      "guest_names": [],
      "merch_status": null
    },
    "result_type": "article"
  },
  {
    "id": "bd3c312e4a98ceccecabbeceb537559f6814da13",
    "title": "Keanu Reeves Stars as Lead Character in Masashi Kawamura\u2019s HIDARI Stop-Motion Animated Film",
    "url": "https://anitrendz.net/news/2026/05/18/keanu-reeves-stars-as-lead-character-in-masashi-kawamuras-hidari-stop-motion-animated-film/?utm_source=rss&utm_medium=rss&utm_campaign=keanu-reeves-stars-as-lead-character-in-masashi-kawamuras-hidari-stop-motion-animated-film",
    "source_name": "Anime Trending",
    "source_type": "rss",
    "published_at": "2026-05-18T21:42:31Z",
    "summary": "Actor Keanu Reeves has been cast as the lead character for Masashi Kawamura\u2019s HIDARI feature-length stop-motion samurai animated film",
    "content": "",
    "categories": [
      "anime",
      "manga",
      "events",
      "games"
    ],
    "tags": [],
    "entity_tags": [],
    "region_tags": [],
    "sg_relevance": 0.0,
    "freshness_score": 0.8097208148967661,
    "home_score": 0.6314,
    "source_quality": 0.78,
    "image_url": null,
    "event_metadata": null,
    "result_type": "article"
  },
  {
    "id": "cbf0dd14283f102b9a6038d3cb6a391fc359da3f",
    "title": "Nephew qualifies for Street Fighter 6 Esports World Cup alongside Kobayan, while the twins fulfill their destiny in 2XKO: The week before Combo Breaker 2026",
    "url": "https://esportsinsider.com/2026/05/fgc-qualifications-ewc-dreamhack-recap",
    "source_name": "Esports Insider",
    "source_type": "rss",
    "published_at": "2026-05-18T17:55:41Z",
    "summary": "This week, the FGC has been relatively mellow compared to the Evo Japan week, but that might be what the community needs before the gargantuan event this weekend: Combo Breaker 202",
    "content": "",
    "categories": [
      "esports",
      "games",
      "events"
    ],
    "tags": [],
    "entity_tags": [
      "Street Fighter 6"
    ],
    "region_tags": [
      "SEA"
    ],
    "sg_relevance": 0.08,
    "freshness_score": 0.7683011392976661,
    "home_score": 0.6312,
    "source_quality": 0.77,
    "image_url": null,
    "event_metadata": null,
    "result_type": "article"
  },
  {
    "id": "de28a95c108b4243b5690b2aead8be4b0075c8ab",
    "title": "New PlayStation Plus Subscriptions Will Cost More",
    "url": "https://www.siliconera.com/new-playstation-plus-subscriptions-will-cost-more/",
    "source_name": "Siliconera",
    "source_type": "rss",
    "published_at": "2026-05-18T20:00:00Z",
    "summary": "The cost of PlayStation Plus subscriptions is going up, with Sony blaming \"ongoing market conditions\" for the change",
    "content": "",
    "categories": [
      "games",
      "anime",
      "merch",
      "events"
    ],
    "tags": [],
    "entity_tags": [],
    "region_tags": [],
    "sg_relevance": 0.0,
    "freshness_score": 0.7907321591076352,
    "home_score": 0.6288,
    "source_quality": 0.82,
    "image_url": null,
    "event_metadata": null,
    "result_type": "article"
  },
  {
    "id": "e1721ef89c716841e4792b526589fc45a03a9876",
    "title": "Street Fighter 6 announces Random Avatar Matches and Avatar Arcade modes",
    "url": "https://nintendoeverything.com/street-fighter-6-announces-random-avatar-matches-and-avatar-arcade-modes/",
    "source_name": "Nintendo Everything",
    "source_type": "rss",
    "published_at": "2026-05-19T00:53:33Z",
    "summary": "Two new modes are on the way to Street Fighter 6 \u2013 specifically Random Avatar Matches and Avatar Arcade",
    "content": "",
    "categories": [
      "games",
      "anime",
      "merch"
    ],
    "tags": [],
    "entity_tags": [
      "Street Fighter 6"
    ],
    "region_tags": [],
    "sg_relevance": 0.0,
    "freshness_score": 0.8463309523061423,
    "home_score": 0.6283,
    "source_quality": 0.77,
    "image_url": null,
    "event_metadata": {
      "event_type": null,
      "date_label": "May 28, 2026",
      "venue": null,
      "ticket_status": null,
      "ticket_url": null,
      "guest_status": null,
      "guest_names": [],
      "merch_status": null
    },
    "result_type": "article"
  },
  {
    "id": "adc8672bf477d19635802665612f90dac1bb498f",
    "title": "The Adventures of Elliot: The Millennium Tales releases \u201cPrologue Demo\u201d, new trailer",
    "url": "https://nintendoeverything.com/the-adventures-of-elliot-the-millennium-tales-releases-prologue-demo-new-trailer/",
    "source_name": "Nintendo Everything",
    "source_type": "rss",
    "published_at": "2026-05-19T00:16:09Z",
    "summary": "Ahead of its launch next month, a brand new \u201cPrologue Demo\u201d has just come out for The Adventures of Elliot: The Millennium Tales",
    "content": "",
    "categories": [
      "games",
      "anime",
      "merch"
    ],
    "tags": [],
    "entity_tags": [],
    "region_tags": [],
    "sg_relevance": 0.0,
    "freshness_score": 0.839035543368996,
    "home_score": 0.6251,
    "source_quality": 0.77,
    "image_url": null,
    "event_metadata": null,
    "result_type": "article"
  },
  {
    "id": "94f64c53e63bd4e85866e0ff7eb025eeb4e13014",
    "title": "Dissidia Duellum Final Fantasy Update Arrives This Week",
    "url": "https://www.siliconera.com/dissidia-duellum-final-fantasy-update-arrives-this-week/",
    "source_name": "Siliconera",
    "source_type": "rss",
    "published_at": "2026-05-18T19:00:00Z",
    "summary": "We'll hear more about the future of Dissidia Duellum Final Fantasy and perhaps more about characters in an update presentation this week",
    "content": "",
    "categories": [
      "games",
      "anime",
      "merch",
      "events"
    ],
    "tags": [],
    "entity_tags": [
      "Final Fantasy"
    ],
    "region_tags": [],
    "sg_relevance": 0.0,
    "freshness_score": 0.7798256815287462,
    "home_score": 0.6239,
    "source_quality": 0.82,
    "image_url": null,
    "event_metadata": null,
    "result_type": "article"
  },
  {
    "id": "d45ab42034221fb116bca582038a19799204e0b1",
    "title": "One Peace Books Acquires My Sweet Marriage to My Ex-Nemesis Manga for Release in March 2027",
    "url": "https://anitrendz.net/news/2026/05/18/one-peace-books-acquires-my-sweet-marriage-to-my-ex-nemesis-manga-for-release-in-march-2027/?utm_source=rss&utm_medium=rss&utm_campaign=one-peace-books-acquires-my-sweet-marriage-to-my-ex-nemesis-manga-for-release-in-march-2027",
    "source_name": "Anime Trending",
    "source_type": "rss",
    "published_at": "2026-05-18T19:57:38Z",
    "summary": "One Peace Books announced last week, via Behind the Manga, that it has licensed the romantic comedy manga series My Sweet Marriage to My Ex-Nemesis",
    "content": "",
    "categories": [
      "anime",
      "manga",
      "events",
      "games"
    ],
    "tags": [],
    "entity_tags": [],
    "region_tags": [],
    "sg_relevance": 0.0,
    "freshness_score": 0.7902986912938496,
    "home_score": 0.6226,
    "source_quality": 0.78,
    "image_url": null,
    "event_metadata": null,
    "result_type": "article"
  },
  {
    "id": "8e2de769712c5cfaf399e5212b0e63516bf717fa",
    "title": "Kappei Yamaguchi & Yoshiko Sakakibara Join Voice Cast of Daemons of the Shadow Realm",
    "url": "https://anitrendz.net/news/2026/05/18/kappei-yamaguchi-yoshiko-sakakibara-join-voice-cast-of-daemons-of-the-shadow-realm/?utm_source=rss&utm_medium=rss&utm_campaign=kappei-yamaguchi-yoshiko-sakakibara-join-voice-cast-of-daemons-of-the-shadow-realm",
    "source_name": "Anime Trending",
    "source_type": "rss",
    "published_at": "2026-05-18T19:22:31Z",
    "summary": "Two additional cast members have joined the currently airing Daemons of the Shadow Realm TV anime series",
    "content": "",
    "categories": [
      "anime",
      "manga",
      "events"
    ],
    "tags": [],
    "entity_tags": [],
    "region_tags": [],
    "sg_relevance": 0.0,
    "freshness_score": 0.7839005043923603,
    "home_score": 0.6198,
    "source_quality": 0.78,
    "image_url": null,
    "event_metadata": null,
    "result_type": "article"
  },
  {
    "id": "de20cfb6cf68912ca269597c8cd8b3e749a9e205",
    "title": "Manga Mavericks Books Licenses Zawayuki Taki\u2019s Tie Me Up, Stare Me Down Manga for May 2027 Release",
    "url": "https://anitrendz.net/news/2026/05/18/manga-mavericks-books-licenses-zawayuki-takis-tie-me-up-stare-me-down-manga-for-may-2027-release/?utm_source=rss&utm_medium=rss&utm_campaign=manga-mavericks-books-licenses-zawayuki-takis-tie-me-up-stare-me-down-manga-for-may-2027-release",
    "source_name": "Anime Trending",
    "source_type": "rss",
    "published_at": "2026-05-18T19:15:00Z",
    "summary": "Manga Mavericks Books has announced the license acquisition of Zawayuki Taki\u2019s Tie Me Up, Stare Me Down manga series during its online Manga Mavericks Monday licensing event",
    "content": "",
    "categories": [
      "anime",
      "manga",
      "events",
      "games"
    ],
    "tags": [],
    "entity_tags": [],
    "region_tags": [],
    "sg_relevance": 0.0,
    "freshness_score": 0.7825377264672827,
    "home_score": 0.6191,
    "source_quality": 0.78,
    "image_url": null,
    "event_metadata": null,
    "result_type": "article"
  },
  {
    "id": "f714c3d50654e38a31f95b994ad4aa2c2b26dce4",
    "title": "Next Bexide Mountain Game Is Namco Legendary Mountains",
    "url": "https://www.siliconera.com/next-bexide-mountain-game-is-namco-legendary-mountains/",
    "source_name": "Siliconera",
    "source_type": "rss",
    "published_at": "2026-05-18T18:00:00Z",
    "summary": "Fruit Mountain developer Bexide is behind a matching puzzle game with Pac-Man and Dig Dug called Namco Legendary Mountains",
    "content": "",
    "categories": [
      "games",
      "anime",
      "merch",
      "events"
    ],
    "tags": [],
    "entity_tags": [],
    "region_tags": [],
    "sg_relevance": 0.0,
    "freshness_score": 0.7690696357683567,
    "home_score": 0.6191,
    "source_quality": 0.82,
    "image_url": null,
    "event_metadata": null,
    "result_type": "article"
  },
  {
    "id": "f7172fe8ddf5bbead0afc5963ad997ced12ab8ba",
    "title": "Pokemon Deluxe Character Guide Limited Edition pre-orders return after selling out, plus discount available",
    "url": "https://nintendoeverything.com/pokemon-deluxe-character-guide-limited-edition-pre-orders-return-after-selling-out-plus-discount-available/",
    "source_name": "Nintendo Everything",
    "source_type": "rss",
    "published_at": "2026-05-18T19:00:24Z",
    "summary": "Good news for Pokemon fans: if you missed out on the Pokemon Deluxe Character Guide Limited Edition after pre-orders went live a few days ago, they\u2019re available once again",
    "content": "",
    "categories": [
      "games",
      "anime",
      "merch"
    ],
    "tags": [],
    "entity_tags": [],
    "region_tags": [],
    "sg_relevance": 0.08,
    "freshness_score": 0.7798977244457664,
    "home_score": 0.6185,
    "source_quality": 0.77,
    "image_url": null,
    "event_metadata": {
      "event_type": null,
      "date_label": null,
      "venue": null,
      "ticket_status": "Sold out",
      "ticket_url": null,
      "guest_status": null,
      "guest_names": [],
      "merch_status": null
    },
    "result_type": "article"
  },
  {
    "id": "205d15f86c6e5d31eab381bcd19592621d99153b",
    "title": "The Oblivious Saint Can\u2019t Contain Her Power Premieres in July",
    "url": "https://blog.jlist.com/news/the-oblivious-saint-cant-contain-her-power-premieres-in-july/",
    "source_name": "J-List Blog",
    "source_type": "rss",
    "published_at": "2026-05-18T14:30:00Z",
    "summary": "The Oblivious Saint Can\u2019t Contain Her Power has received a new trailer and visual ahead of its July premiere",
    "content": "",
    "categories": [
      "anime",
      "manga",
      "merch",
      "events",
      "games"
    ],
    "tags": [],
    "entity_tags": [],
    "region_tags": [],
    "sg_relevance": 0.08,
    "freshness_score": 0.7325780545998991,
    "home_score": 0.6167,
    "source_quality": 0.78,
    "image_url": null,
    "event_metadata": null,
    "result_type": "article"
  },
  {
    "id": "3d99e2733a9e51820c44a78b0a97a6070ec0d38f",
    "title": "Ushiro no Shomen Kamui-san Previews KOTOKO Ending Theme Song in New Trailer",
    "url": "https://anitrendz.net/news/2026/05/18/ushiro-no-shomen-kamui-san-previews-kotoko-ending-theme-song-in-new-trailer/?utm_source=rss&utm_medium=rss&utm_campaign=ushiro-no-shomen-kamui-san-previews-kotoko-ending-theme-song-in-new-trailer",
    "source_name": "Anime Trending",
    "source_type": "rss",
    "published_at": "2026-05-18T18:34:09Z",
    "summary": "A short new teaser trailer has been unveiled for the upcoming Ushiro no Shomen Kamui-san TV anime series, previewing the show\u2019s main ending theme song",
    "content": "",
    "categories": [
      "anime",
      "manga",
      "events"
    ],
    "tags": [],
    "entity_tags": [],
    "region_tags": [],
    "sg_relevance": 0.0,
    "freshness_score": 0.7751729094875706,
    "home_score": 0.6158,
    "source_quality": 0.78,
    "image_url": null,
    "event_metadata": null,
    "result_type": "article"
  },
  {
    "id": "64f7c86c8580f9172dbcefb5a5fb63a90a909b45",
    "title": "Aerith, Cloud, and Tifa Wear Dresses in Official FFVII Ever Crisis Wallpapers",
    "url": "https://www.siliconera.com/aerith-cloud-and-tifa-wear-dresses-in-official-ffvii-ever-crisis-wallpapers/",
    "source_name": "Siliconera",
    "source_type": "rss",
    "published_at": "2026-05-18T17:00:00Z",
    "summary": "As the FFVII Ever Crisis Corneo Cup event draws to a close, wallpapers of Aerith, Cloud, and Tifa in their dresses dropped",
    "content": "",
    "categories": [
      "games",
      "anime",
      "merch",
      "events"
    ],
    "tags": [],
    "entity_tags": [],
    "region_tags": [],
    "sg_relevance": 0.0,
    "freshness_score": 0.7584619468315633,
    "home_score": 0.6143,
    "source_quality": 0.82,
    "image_url": null,
    "event_metadata": null,
    "result_type": "article"
  },
  {
    "id": "2778be056df88ddd6c74ebd1a01ea9097bfd98d5",
    "title": "Rascal Does Not Dream of a Dear Friend Spotlights Sara in Latest Visual",
    "url": "https://anitrendz.net/news/2026/05/18/rascal-does-not-dream-of-a-dear-friend-spotlights-sara-in-latest-visual/?utm_source=rss&utm_medium=rss&utm_campaign=rascal-does-not-dream-of-a-dear-friend-spotlights-sara-in-latest-visual",
    "source_name": "Anime Trending",
    "source_type": "rss",
    "published_at": "2026-05-18T18:00:59Z",
    "summary": "The latest memorial visual has been released for the upcoming Rascal Does Not Dream of a Dear Friend anime film, spotlighting Sara Himeji",
    "content": "",
    "categories": [
      "anime",
      "manga",
      "events",
      "games"
    ],
    "tags": [],
    "entity_tags": [],
    "region_tags": [],
    "sg_relevance": 0.0,
    "freshness_score": 0.7692443294255908,
    "home_score": 0.6132,
    "source_quality": 0.78,
    "image_url": null,
    "event_metadata": null,
    "result_type": "article"
  },
  {
    "id": "b31bd90af9194bd1834110ab45ee2691ddfd9956",
    "title": "Granblue Fantasy: Relink \u2013 Endless Ragnarok Introduces Returning Characters",
    "url": "https://rpgamer.com/2026/05/granblue-fantasy-relink-endless-ragnarok-introduces-returning-characters/",
    "source_name": "RPGamer",
    "source_type": "rss",
    "published_at": "2026-05-18T16:56:14Z",
    "summary": "Cygames has released trailers for the numerous returning playable characters in Granblue Fantasy: Relink \u2013 Endless Ragnarok , the upcoming enhanced version of action RPG Granblue F",
    "content": "",
    "categories": [
      "games",
      "anime",
      "events"
    ],
    "tags": [],
    "entity_tags": [],
    "region_tags": [],
    "sg_relevance": 0.0,
    "freshness_score": 0.7578007534707035,
    "home_score": 0.611,
    "source_quality": 0.8,
    "image_url": null,
    "event_metadata": {
      "event_type": null,
      "date_label": "July 9, 2026",
      "venue": null,
      "ticket_status": null,
      "ticket_url": null,
      "guest_status": null,
      "guest_names": [],
      "merch_status": null
    },
    "result_type": "article"
  },
  {
    "id": "cf730a6b6d16f94a00568d133dacb3afcdf10027",
    "title": "Persona 3 Reload Localization Survey Asks About Its Translation",
    "url": "https://www.siliconera.com/persona-3-reload-localization-survey-asks-about-its-translation/",
    "source_name": "Siliconera",
    "source_type": "rss",
    "published_at": "2026-05-18T16:00:00Z",
    "summary": "Atlus shared a Persona 3 Reload localization survey asking for feedback on the dialogue, character, menu, and UI translation in the JRPG",
    "content": "",
    "categories": [
      "games",
      "anime",
      "merch",
      "events"
    ],
    "tags": [
      "jrpg"
    ],
    "entity_tags": [
      "Persona",
      "Atlus"
    ],
    "region_tags": [],
    "sg_relevance": 0.0,
    "freshness_score": 0.7480005685009518,
    "home_score": 0.6096,
    "source_quality": 0.82,
    "image_url": null,
    "event_metadata": null,
    "result_type": "article"
  },
  {
    "id": "6597e01538e727359119d8af446759f4d555d542",
    "title": "BOCCHI THE ROCK! Manga Resumes Serialization in June",
    "url": "https://crunchyroll.com/news/latest/2026/5/18/bocchi-the-rock-manga-resume-serialization-june-2026",
    "source_name": "Crunchyroll News",
    "source_type": "rss",
    "published_at": "2026-05-18T16:31:00Z",
    "summary": "The manga will return in Manga Time Kirara MAX's August issue",
    "content": "",
    "categories": [
      "anime",
      "manga",
      "games",
      "events"
    ],
    "tags": [],
    "entity_tags": [],
    "region_tags": [],
    "sg_relevance": 0.0,
    "freshness_score": 0.753387186383242,
    "home_score": 0.6075,
    "source_quality": 0.79,
    "image_url": null,
    "event_metadata": null,
    "result_type": "article"
  },
  {
    "id": "f33683644741e8f18a04bae66590be74c8862621",
    "title": "Iyapan Returns, Episode 2 \u2014 Demon Lady\u2019s Hopes and Knickers Take a Twisted Turn",
    "url": "https://blog.jlist.com/featured/iyapan-returns-episode-2-demon-ladys-hopes-and-knickers-take-a-twisted-turn/",
    "source_name": "J-List Blog",
    "source_type": "rss",
    "published_at": "2026-05-18T20:30:00Z",
    "summary": "Demon Lady Valmina greets the Hero with a romantic offer, but his shocking counteroffer stuns her",
    "content": "",
    "categories": [
      "anime",
      "manga",
      "merch",
      "games"
    ],
    "tags": [],
    "entity_tags": [],
    "region_tags": [],
    "sg_relevance": 0.0,
    "freshness_score": 0.7962420559505198,
    "home_score": 0.6073,
    "source_quality": 0.78,
    "image_url": "https://bimgs.jlist.com/wp-content/uploads/2026/05/Iyapan-Returns-Episode-2-Hero-Enters-Demon-Lady-Throne-Room.mp4",
    "event_metadata": null,
    "result_type": "article"
  },
  {
    "id": "bc602e967f5074d8b2f2d3a22da120f71059e7c6",
    "title": "Fortnite Esports World Cup (EWC) 2026: All qualified teams",
    "url": "https://esports.gg/news/fortnite/fortnite-ewc-2026-all-qualified-teams/",
    "source_name": "Esports.gg",
    "source_type": "rss",
    "published_at": "2026-05-18T15:36:15Z",
    "summary": "Fortnite Reload heads to the 2026 Esports World Cup (EWC)",
    "content": "",
    "categories": [
      "esports",
      "games"
    ],
    "tags": [],
    "entity_tags": [],
    "region_tags": [
      "SEA"
    ],
    "sg_relevance": 0.08,
    "freshness_score": 0.7438992454803803,
    "home_score": 0.6068,
    "source_quality": 0.76,
    "image_url": "https://cdn.esports.gg/wp-content/uploads/2021/02/13122740/cropped-esports-gg-favicon-1-32x32.png",
    "event_metadata": null,
    "result_type": "article"
  },
  {
    "id": "97b451f65fbc6c70b915b1cb8c2c834b795c6864",
    "title": "The Expanse: Osiris Reborn Impression",
    "url": "https://rpgamer.com/2026/05/the-expanse-osiris-reborn-impression/",
    "source_name": "RPGamer",
    "source_type": "rss",
    "published_at": "2026-05-18T16:01:47Z",
    "summary": "It's only a small sample, but what I've seen from The Expanse: Osiris Reborn 's closed beta is impressive, and I'm very much looking forward to seeing the full game",
    "content": "",
    "categories": [
      "games",
      "anime",
      "events"
    ],
    "tags": [],
    "entity_tags": [],
    "region_tags": [],
    "sg_relevance": 0.0,
    "freshness_score": 0.7483092402178746,
    "home_score": 0.6067,
    "source_quality": 0.8,
    "image_url": null,
    "event_metadata": null,
    "result_type": "article"
  },
  {
    "id": "36f0480dd46a73e23c2ed4ddf78385c9328442e7",
    "title": "Goddess of Victory: NIKKE Animated Shorts Start Airing This Week",
    "url": "https://www.siliconera.com/goddess-of-victory-nikke-animated-shorts-start-airing-this-week/",
    "source_name": "Siliconera",
    "source_type": "rss",
    "published_at": "2026-05-18T15:00:00Z",
    "summary": "There's still no proper Goddess of Victory: NIKKE anime yet, but a new animated shorts series starts this week",
    "content": "",
    "categories": [
      "games",
      "anime",
      "merch",
      "events"
    ],
    "tags": [],
    "entity_tags": [],
    "region_tags": [],
    "sg_relevance": 0.0,
    "freshness_score": 0.7376834827546613,
    "home_score": 0.605,
    "source_quality": 0.82,
    "image_url": null,
    "event_metadata": null,
    "result_type": "article"
  },
  {
    "id": "325ae2c2bd069bd0de0821151dd06585e60905fc",
    "title": "Kugayama Shiori\u2019s Death Diary Review \u2013 Just, Hangin Out",
    "url": "https://noisypixel.net/kugayama-shioris-death-diary-supernatural-mystery-review/",
    "source_name": "Noisy Pixel",
    "source_type": "rss",
    "published_at": "2026-05-18T16:00:32Z",
    "summary": "What if a ghost is losing their memories and decides to try dying again and again to see if perhaps something comes back to them? The premise of Laplacian\u2019s latest work is Kugayama",
    "content": "",
    "categories": [
      "games",
      "anime",
      "merch",
      "events"
    ],
    "tags": [],
    "entity_tags": [],
    "region_tags": [],
    "sg_relevance": 0.0,
    "freshness_score": 0.7480927721937433,
    "home_score": 0.6036,
    "source_quality": 0.78,
    "image_url": null,
    "event_metadata": null,
    "result_type": "article"
  },
  {
    "id": "fa598d5251c9c5f263b23d879d282cc8dfdd942d",
    "title": "Creating the Final Fantasy VII Rebirth Switch 2 and Xbox Ports",
    "url": "https://crunchyroll.com/news/interviews/2026/5/18/final-fantasy-vii-rebirth-ports-interview",
    "source_name": "Crunchyroll News",
    "source_type": "rss",
    "published_at": "2026-05-18T15:00:00Z",
    "summary": "Creating the Final Fantasy VII Rebirth Switch 2 and Xbox Ports",
    "content": "",
    "categories": [
      "anime",
      "manga",
      "games",
      "events"
    ],
    "tags": [],
    "entity_tags": [
      "Final Fantasy"
    ],
    "region_tags": [],
    "sg_relevance": 0.0,
    "freshness_score": 0.7376832055143632,
    "home_score": 0.6005,
    "source_quality": 0.79,
    "image_url": null,
    "event_metadata": null,
    "result_type": "article"
  },
  {
    "id": "8c20b9e5075abe4c8af4d4661c43bd30d0215080",
    "title": "Crunchyroll News Puzzles Vol. 55: Coming in Hot and Ramen Powered",
    "url": "https://crunchyroll.com/news/quizzes/2026/5/18/anime-crosswords-puzzles-vol-55",
    "source_name": "Crunchyroll News",
    "source_type": "rss",
    "published_at": "2026-05-18T15:00:00Z",
    "summary": "Test your anime knowledge with our latest puzzle collection!",
    "content": "",
    "categories": [
      "anime",
      "manga",
      "games",
      "events"
    ],
    "tags": [],
    "entity_tags": [],
    "region_tags": [],
    "sg_relevance": 0.0,
    "freshness_score": 0.7376832048768592,
    "home_score": 0.6005,
    "source_quality": 0.79,
    "image_url": null,
    "event_metadata": null,
    "result_type": "article"
  },
  {
    "id": "7f3ea02a9bed860addeba46424438cef98cf6177",
    "title": "New Witch on the Holy Night Movie Character Art Revealed",
    "url": "https://www.siliconera.com/new-witch-on-the-holy-night-movie-character-art-revealed/",
    "source_name": "Siliconera",
    "source_type": "rss",
    "published_at": "2026-05-18T14:00:47Z",
    "summary": "The movie is slated to appear in Japanese theaters in 2026",
    "content": "",
    "categories": [
      "games",
      "anime",
      "merch",
      "events"
    ],
    "tags": [],
    "entity_tags": [],
    "region_tags": [],
    "sg_relevance": 0.0,
    "freshness_score": 0.7276406285920763,
    "home_score": 0.6004,
    "source_quality": 0.82,
    "image_url": null,
    "event_metadata": null,
    "result_type": "article"
  },
  {
    "id": "76cfb9d73095f58893a0f504a214becfe12a8ea9",
    "title": "Hardest and Most Annoying JRPG Achievements of All Time",
    "url": "https://www.dualshockers.com/most-annoying-jrpg-achievements/",
    "source_name": "DualShockers",
    "source_type": "rss",
    "published_at": "2026-05-18T19:30:23Z",
    "summary": "From real-time item decay to 60,000 enemy kills, these JRPG achievements are some of the most punishing completion challenges ever designed",
    "content": "",
    "categories": [
      "games",
      "anime",
      "merch"
    ],
    "tags": [
      "jrpg"
    ],
    "entity_tags": [],
    "region_tags": [],
    "sg_relevance": 0.0,
    "freshness_score": 0.785329365092738,
    "home_score": 0.5979,
    "source_quality": 0.75,
    "image_url": "https://static0.dualshockersimages.com/wordpress/wp-content/uploads/2026/05/thumbnail-6.jpg",
    "event_metadata": null,
    "result_type": "article"
  },
  {
    "id": "26f2d9133896e93f23994e105f65b968cdca3591",
    "title": "Post-Vivarium, Ado Speaks on Revealing Her Identity to the Public: \u2018I\u2019m Not Thinking About That at All Right Now\u2019",
    "url": "https://animecorner.me/post-vivarium-ado-speaks-on-revealing-her-identity-to-the-public-im-not-thinking-about-that-at-all-right-now/",
    "source_name": "Anime Corner",
    "source_type": "rss",
    "published_at": "2026-05-18T14:05:13Z",
    "summary": "Ado spoke to Pasadena Star-News ahead of her performance at Zipangu on May 16,\u2026",
    "content": "",
    "categories": [
      "anime",
      "manga",
      "events",
      "games"
    ],
    "tags": [],
    "entity_tags": [],
    "region_tags": [],
    "sg_relevance": 0.0,
    "freshness_score": 0.7283874979602865,
    "home_score": 0.5978,
    "source_quality": 0.8,
    "image_url": null,
    "event_metadata": {
      "event_type": null,
      "date_label": "May 16",
      "venue": null,
      "ticket_status": null,
      "ticket_url": null,
      "guest_status": null,
      "guest_names": [],
      "merch_status": null
    },
    "result_type": "article"
  },
  {
    "id": "4692be9545beaa9c1b645063092ca30d3cf9f29e",
    "title": "Interview: Holostars Vtuber Goldbullet Discusses His Hollow-Heart Horror Series",
    "url": "https://www.siliconera.com/interview-holostars-vtuber-goldbullet-discusses-his-hollow-heart-horror-series/",
    "source_name": "Siliconera",
    "source_type": "rss",
    "published_at": "2026-05-18T13:00:00Z",
    "summary": "Holostars English Vtuber Goldbullet is working on an animated horror series called Hollow-Heart and spoke with us about the project",
    "content": "",
    "categories": [
      "games",
      "anime",
      "merch",
      "events"
    ],
    "tags": [],
    "entity_tags": [],
    "region_tags": [],
    "sg_relevance": 0.0,
    "freshness_score": 0.7174742560289802,
    "home_score": 0.5959,
    "source_quality": 0.82,
    "image_url": null,
    "event_metadata": null,
    "result_type": "article"
  }
]